{
    "htmlextractedmetarefiners": null,
    "postaladdress": null,
    "formatdetection": null,
    "locationgeo": null,
    "htmlextractedisinmegamenu": "false",
    "htmlextractedhasarticleurlkeywords": "false",
    "httpheadercontentsecuritypolicy": null,
    "licensee": null,
    "documentreference": "https://www.nab.com.au/personal/life-moments/family/buy-car",
    "httpheaderxxssprotection": null,
    "dcdescription": null,
    "dateerror": null,
    "httpheaderxakamaitransformed": null,
    "collectordepth": "0",
    "googlesiteverification": null,
    "taxonomy": null,
    "fbpageid": "174238599281322",
    "ogurl": "https://www.nab.com.au/personal/life-moments/family/buy-car",
    "ogtype": "website",
    "httpheaderxframeoptions": null,
    "collectorreferencedurls": "https://www.nab.com.au/personal/online-banking/fast-payments",
    "collectorreferrerlinktext": null,
    "httpheaderdate": "Tue, 04 Mar 2025 01:59:27 GMT",
    "uripath": null,
    "searchsuggestions": [],
    "ogtitle": "Buying a car",
    "content": "   Skip to login   Skip to main content   Skip to chat   Personal   Life Moments   Life and family   Buying a car   Buying a car   Here\u2019s our guide to paying for your new wheels and keeping up with the day to day costs.  I'm buying a new car   \u200bThe real cost of buying a car   \u200bWe\u2019ll help you uncover the hidden costs of buying a car.  Car dealership finance   \u200bQuestions you should ask before applying for car dealer finance.  \u200bCost saving tips for running your car   How to reduce any unnecessary car expenses.  New car finance options   How to get behind the wheel \u2013 sooner than you might think.  How to budget   Create a budget to help you meet your money goals.  Related products and tools   Car loans   With a loan from us, you can buy your dream car, first car or something in between.  Car Insurance   Compare comprehensive car insurance and third-party cover with NAB Car Insurance.  Personal loan repayment calculator   Calculate what your repayments could be with a NAB Personal Loan.  Get in touch   Customer Support Tool   Solve problems quickly online with our easy-to-follow guides. Simply select a topic and we\u2019ll direct you to the information you need.  Customer Support Tool   Contact us   Explore our personal banking contact information and get support with a wide range of products, services and topics.  View all personal banking contacts   Visit a NAB branch   Visit us in person at your nearest NAB branch or business banking centre.  Find a NAB branch   Important Information   Terms and Conditions  This section contains Important Information relevant to the page you are viewing, but you can't see it because you have JavaScript disabled on your browser.\u00a0Please enable JavaScript and come back so you can see the complete page.\u00a0It's important that you read the Important Information in this section before acting on any information on this page.  Apologies but the Important Information section you are trying to view is not displaying properly at the moment. Please refresh the page or try again later.   Target Market Determinations for these products are available at\u00a0nab.com.au/TMD.  ",
    "httpheaderxcheckcacheable": null,
    "sitename": null,
    "htmlextractedtrainingdatacategory": null,
    "htmlextractedhasbenefitsandfeatures": null,
    "phone": null,
    "htmlextractedh1": [
        "Buying a car"
    ],
    "email": null,
    "access": null,
    "breadcrumb": null,
    "htmlextractedhasgetstarted": "false",
    "uriparams": null,
    "htmlextractedhasarticletags": null,
    "principlename": null,
    "facebook": null,
    "origintrial": null,
    "contenttypehint": null,
    "age": null,
    "documentcontenttype": "text/html",
    "contentencoding": "UTF-8",
    "viewport": null,
    "htmlextractedfieldtemplate": "/conf/nab/settings/wcm/templates/content-category",
    "contentpurpose": null,
    "httpheadercontentencoding": null,
    "urihost": null,
    "advisernames": null,
    "collectorsitemaplastmod": "1739942074000",
    "fax": null,
    "httpheadercachecontrol": "max-age=1195",
    "httpheadercontentlength": null,
    "uripathparseerror": null,
    "created": null,
    "description": "Buying a car? We'll show you some finance options along with cost saving tips on running your car.",
    "findlocationid": null,
    "robots": "index,follow",
    "htmlextractedurlkeywords": "https www nab com au personal life moments family buy car",
    "httpheaderxcontenttypeoptions": null,
    "id": "bmFiY3E1Y3VycmVudF9odHRwczovL3d3dy5uYWIuY29tLmF1L3BlcnNvbmFsL2xpZmUtbW9tZW50cy9mYW1pbHkvYnV5LWNhcg",
    "crawltime": "2025-03-04T01:59:36Z",
    "collectorcontenttype": "text/html",
    "searchrefiners": null,
    "website": null,
    "fallbacksnippet": null,
    "twittertitle": "Buying a car",
    "htmlextractedhastoolsurlkeywords": "false",
    "collectorcontentencoding": "utf-8",
    "collection": [
        "nabcq5current"
    ],
    "datepublished": null,
    "path": "DOMAINSTART/personal/life-moments/family/buy-car",
    "htmlextractedoutboundlinkcount": "346",
    "twittercard": "summary",
    "principleimage": null,
    "xuacompatible": null,
    "documentcontentencoding": "utf-8",
    "lastmodified": "2025-03-04T01:59:36Z",
    "datasource": "www.nab.com.au",
    "htmlextractedhasenquire": "false",
    "latitude": null,
    "xparsedby": "org.apache.tika.parser.DefaultParser",
    "fbadmins": null,
    "encoding": null,
    "state": null,
    "uriprotocol": null,
    "datepub": null,
    "httpheaderxakamaipragmaclientip": null,
    "twittersite": "@nab",
    "extension": "html",
    "httpheadersetcookie": null,
    "collectoriscrawlnew": "true",
    "filename": null,
    "htmlextractedsection": "personal",
    "editor": null,
    "httpheaderetag": null,
    "linkedin": null,
    "searchrefinersall": [],
    "htmlextractedishowto": null,
    "htmlextractedurlsegmentcount": "4",
    "collectorreferrerreference": null,
    "httpheaderstricttransportsecurity": null,
    "topicarea": null,
    "suburb": null,
    "address": null,
    "htmlextractedhasproductdiv": "false",
    "htmlextractedhasbenefitandfeaturestext": "false",
    "httpheaderconnection": "keep-alive",
    "modified": "2025-03-04T01:59:36Z",
    "htmlextractedhasgetincontact": "false",
    "keywords": [],
    "systemtitle": null,
    "category": null,
    "pdfdocinfosubject": null,
    "htmlextractedh3": [
        "Tools and calculators",
        "You may be interested in",
        "View our research and insights hub",
        "$0 international transfer fee",
        "New Get a 6-month free trial with NAB Bookkeeper",
        "You might be interested in",
        "Unsecured business finance",
        "Related tools and calculators",
        "Offer 200,000 bonus Qantas Points",
        "Related tools and help",
        "Related tools and help",
        "NAB Connect training",
        "$0 international transfer fees",
        "More about sustainability",
        "Need more help?",
        "Troubleshooting guides",
        "Need more help?",
        "\u00e2\u0080\u008bThe real cost of buying a car",
        "Car dealership finance",
        "\u00e2\u0080\u008bCost saving tips for running your car",
        "New car finance options",
        "How to budget",
        "Car loans",
        "Car Insurance",
        "Personal loan repayment calculator",
        "Customer Support Tool",
        "Contact us",
        "Visit a NAB branch",
        "Terms and Conditions"
    ],
    "principletitle": null,
    "location": null,
    "httpheaderacceptranges": null,
    "httpheadertransferencoding": null,
    "subcollection": [],
    "summary": null,
    "httpheadervary": "Accept-Encoding",
    "dctitle": "Buying a car | Help and guidance - NAB",
    "twitter": null,
    "tags": null,
    "docsize": null,
    "url": "https://www.nab.com.au/personal/life-moments/family/buy-car",
    "htmlextractedhasapplynow": "false",
    "contenttype": "text/html",
    "crawledat": "1741053576707",
    "title": "Buying a car",
    "httpheaderexpires": null,
    "httpheaderxserial": null,
    "httpheaderxakamaisslclientsid": null,
    "twitteraccountid": "7302852",
    "ogdescription": "Looking for a new car? Read our tips on buying a car. You'll learn about finance options along with cost saving tips to reduce expenses on running your car.",
    "htmlextractedhasgettingstarted": "false",
    "date": "Tue, 04 Mar 2025 01:59:31 GMT",
    "htmlextractedinputcount": "2",
    "collectorreferrerlinktag": null,
    "postcode": null,
    "contentfamily": "html",
    "document": null,
    "author": null,
    "contentlocation": "https://www.nab.com.au/personal/life-moments/family/buy-car",
    "metachecksum": null,
    "longitude": null,
    "htmlextractedh2": [
        "Latest offers",
        "Update your browser.",
        "NAB Mobile Banking app",
        "Apply for NAB Now Pay Later in under 90 seconds",
        "Women in Business",
        "The Morning Call Podcast",
        "The Morning Call Podcast",
        "Helping you stay safe from scams",
        "I'm buying a new car",
        "Related products and tools",
        "Get in touch",
        "Important Information",
        "Quick links",
        "Quick links",
        "Policies and terms",
        "Policies and terms",
        "Connect with us",
        "Connect with us"
    ],
    "documentcontentfamily": "html",
    "httpheadercontenttype": "text/html;charset=utf-8",
    "httpheaderlastmodified": null,
    "twitterdescription": "Looking for a new car? Read our tips on buying a car. You'll learn about finance options along with cost saving tips to reduce expenses on running your car."
}