{
    "htmlextractedmetarefiners": null,
    "postaladdress": null,
    "formatdetection": null,
    "locationgeo": null,
    "htmlextractedisinmegamenu": "false",
    "htmlextractedhasarticleurlkeywords": "false",
    "httpheadercontentsecuritypolicy": null,
    "licensee": null,
    "documentreference": "https://www.nab.com.au/personal/super-and-investments/nab-adviser-portal",
    "httpheaderxxssprotection": null,
    "dcdescription": null,
    "dateerror": null,
    "httpheaderxakamaitransformed": null,
    "collectordepth": "0",
    "googlesiteverification": null,
    "taxonomy": null,
    "fbpageid": "174238599281322",
    "ogurl": "https://www.nab.com.au/personal/super-and-investments/nab-adviser-portal",
    "ogtype": "website",
    "httpheaderxframeoptions": null,
    "collectorreferencedurls": "https://www.nab.com.au/personal/online-banking/fast-payments",
    "collectorreferrerlinktext": null,
    "httpheaderdate": "Wed, 05 Mar 2025 05:18:52 GMT",
    "uripath": null,
    "searchsuggestions": [],
    "ogtitle": "Cash and deposit solutions",
    "content": "   Skip to login   Skip to main content   Skip to chat     Personal     Super and investments     NAB Adviser Portal   Cash and deposit solutions   To help manage your clients\u2019 investments.    What we offer       A convenient cash hub for your clients' investment cashflow        Easy access to your clients' account information        Dedicated support teams to help you        No monthly fees    Benefits    Our cash and deposit solutions can help you effortlessly manage your clients\u2019 investments and cashflow in one convenient place.    As a financial adviser, NAB Cash Manager Account data feeds can also be linked to your financial planning software so you\u2019ll have real time access to your clients' account information anytime. This means you can easily keep track of your client\u2019s cashflow and provide timely investment advice.    You can also use NAB Connect to view all your clients\u2019 accounts simultaneously in real time. For ease, you\u2019ll be able to:     Download your clients\u2019 transaction history  Access statements  View daily balances    NAB Cash Manager account    The ideal cash hub to manage your clients\u2019 investment cashflow.    Learn more about NAB Cash Manager   Get started    It\u2019s easy, simple and the application process to setup a distribution agreement only takes a few minutes.\u00a0    Set up a distribution agreement    Documents and forms    Access\u00a0documents and forms\u00a0to help you with your clients.    View all forms    Get in touch   Call NAB Cash Manager Servicing   Contact us on 1800 036 171    Monday to Friday, 9am to 5:30pm (AEST/AEDT)    Call investment lending   For investment lending call\u00a01300 135 145    Monday to Friday, 8:30am to 5pm (AEST/AEDT)    Important Information   Terms and Conditions    This section contains Important Information relevant to the page you are viewing, but you can't see it because you have JavaScript disabled on your browser.\u00a0Please enable JavaScript and come back so you can see the complete page.\u00a0It's important that you read the Important Information in this section before acting on any information on this page.    Apologies but the Important Information section you are trying to view is not displaying properly at the moment. Please refresh the page or try again later.   For adviser use only. This information is of a general nature and has been prepared by National Australia Bank Limited ABN 12 004 044 937 (NAB) for information purposes only. The information and documentation contained in this website is current as at 20 March 2018 but may change without notice. The NAB Cash Manager Account is only available to approved customers. Terms and conditions and fees and charges apply. For further information contact NAB. National Australia Bank Limited is the product issuer, unless otherwise specified. Any advice contained in this document has been prepared without taking into account your clients\u2019 objectives, financial situation or needs. Before acting on any advice in this document, NAB recommends that you consider whether it is appropriate for your clients\u2019 circumstances. Use of the information contained on this page is governed by Australian law and is subject to the disclaimers which can be read on the disclaimer page. View the\u00a0NAB Privacy Policy.    Target Market Determination for these products are available at\u00a0nab.com.au/TMD.    ",
    "httpheaderxcheckcacheable": null,
    "sitename": null,
    "htmlextractedtrainingdatacategory": null,
    "htmlextractedhasbenefitsandfeatures": null,
    "phone": null,
    "htmlextractedh1": [
        "Cash and deposit solutions"
    ],
    "email": null,
    "access": null,
    "breadcrumb": null,
    "htmlextractedhasgetstarted": "false",
    "uriparams": null,
    "htmlextractedhasarticletags": null,
    "principlename": null,
    "facebook": null,
    "origintrial": null,
    "contenttypehint": null,
    "age": null,
    "documentcontenttype": "text/html",
    "contentencoding": "UTF-8",
    "viewport": "width=device-width, initial-scale=1",
    "htmlextractedfieldtemplate": "/conf/nab/settings/wcm/templates/service-category-template-new",
    "contentpurpose": null,
    "httpheadercontentencoding": null,
    "urihost": null,
    "advisernames": null,
    "collectorsitemaplastmod": "2024-10-18T23:26:19+11:00",
    "fax": null,
    "httpheadercachecontrol": "max-age=1147",
    "httpheadercontentlength": null,
    "uripathparseerror": null,
    "created": "2025-03-05T16:18:52Z",
    "description": "Cash and investment solutions for your clients to help them manage and grow their wealth.",
    "findlocationid": null,
    "robots": "index,follow",
    "htmlextractedurlkeywords": "https www nab com au personal super and investments nab adviser portal",
    "httpheaderxcontenttypeoptions": null,
    "id": "aHR0cHM6Ly93d3cubmFiLmNvbS5hdS9wZXJzb25hbC9zdXBlci1hbmQtaW52ZXN0bWVudHMvbmFiLWFkdmlzZXItcG9ydGFs",
    "crawltime": "2025-03-05T16:18:56Z",
    "collectorcontenttype": "text/html",
    "searchrefiners": null,
    "website": null,
    "fallbacksnippet": null,
    "twittertitle": "Cash and deposit solutions",
    "htmlextractedhastoolsurlkeywords": "false",
    "collectorcontentencoding": "UTF-8",
    "collection": [
        "nabcq5current"
    ],
    "datepublished": null,
    "path": "DOMAINSTART/personal/super-and-investments/nab-adviser-portal",
    "htmlextractedoutboundlinkcount": "340",
    "twittercard": "summary",
    "principleimage": null,
    "xuacompatible": null,
    "documentcontentencoding": "ISO-8859-1",
    "lastmodified": "2025-03-05T16:18:56Z",
    "datasource": "www.nab.com.au",
    "htmlextractedhasenquire": "false",
    "latitude": null,
    "xparsedby": "org.apache.tika.parser.DefaultParser",
    "fbadmins": null,
    "encoding": null,
    "state": null,
    "uriprotocol": null,
    "datepub": null,
    "httpheaderxakamaipragmaclientip": null,
    "twittersite": "@nab",
    "extension": "html",
    "httpheadersetcookie": null,
    "collectoriscrawlnew": "true",
    "filename": "None",
    "htmlextractedsection": "personal",
    "editor": null,
    "httpheaderetag": null,
    "linkedin": null,
    "searchrefinersall": [],
    "htmlextractedishowto": null,
    "htmlextractedurlsegmentcount": "3",
    "collectorreferrerreference": null,
    "httpheaderstricttransportsecurity": null,
    "topicarea": null,
    "suburb": null,
    "address": null,
    "htmlextractedhasproductdiv": "false",
    "htmlextractedhasbenefitandfeaturestext": "false",
    "httpheaderconnection": "keep-alive",
    "modified": "2025-03-05T16:18:56Z",
    "htmlextractedhasgetincontact": "false",
    "keywords": [],
    "systemtitle": null,
    "category": null,
    "pdfdocinfosubject": null,
    "htmlextractedh3": [
        "Tools and calculators",
        "You may be interested in",
        "View our research and insights hub",
        "$0 international transfer fee",
        "New Get a 6-month free trial with NAB Bookkeeper",
        "You might be interested in",
        "Unsecured business finance",
        "Related tools and calculators",
        "Offer 200,000 bonus Qantas Points",
        "Related tools and help",
        "Related tools and help",
        "NAB Connect training",
        "$0 international transfer fees",
        "More about sustainability",
        "Need more help?",
        "Troubleshooting guides",
        "Need more help?",
        "Call NAB Cash Manager Servicing",
        "Call investment lending",
        "Terms and Conditions"
    ],
    "principletitle": null,
    "location": null,
    "httpheaderacceptranges": null,
    "httpheadertransferencoding": null,
    "subcollection": [],
    "summary": null,
    "httpheadervary": "Accept-Encoding",
    "dctitle": "Cash and deposit solutions | Super and investments - NAB",
    "twitter": null,
    "tags": null,
    "docsize": null,
    "url": "https://www.nab.com.au/personal/super-and-investments/nab-adviser-portal",
    "htmlextractedhasapplynow": "false",
    "contenttype": "text/html",
    "crawledat": "1741151936436",
    "title": "Cash and deposit solutions",
    "httpheaderexpires": null,
    "httpheaderxserial": null,
    "httpheaderxakamaisslclientsid": null,
    "twitteraccountid": "7302852",
    "ogdescription": "Discover how our cash and deposit solutions can help you manage and monitor your clients' investments. Get in touch today to find out how.",
    "htmlextractedhasgettingstarted": "false",
    "date": "Wed, 05 Mar 2025 05:18:52 GMT",
    "htmlextractedinputcount": "2",
    "collectorreferrerlinktag": null,
    "postcode": null,
    "contentfamily": "html",
    "document": null,
    "author": null,
    "contentlocation": "https://www.nab.com.au/personal/super-and-investments/nab-adviser-portal",
    "metachecksum": null,
    "longitude": null,
    "htmlextractedh2": [
        "Latest offers",
        "NAB Mobile Banking app",
        "Update your browser.",
        "Apply for NAB Now Pay Later in under 90 seconds",
        "Women in Business",
        "The Morning Call Podcast",
        "The Morning Call Podcast",
        "Helping you stay safe from scams",
        "What we offer",
        "Benefits",
        "NAB Cash Manager account",
        "Get started",
        "Documents and forms",
        "Get in touch",
        "Important Information",
        "Quick links",
        "Quick links",
        "Policies and terms",
        "Policies and terms",
        "Connect with us",
        "Connect with us"
    ],
    "documentcontentfamily": "html",
    "httpheadercontenttype": "text/html",
    "httpheaderlastmodified": null,
    "twitterdescription": "Discover how our cash and deposit solutions can help you manage and monitor your clients' investments. Get in touch today to find out how."
}