{
    "htmlextractedmetarefiners": null,
    "postaladdress": null,
    "formatdetection": null,
    "locationgeo": null,
    "htmlextractedisinmegamenu": "false",
    "htmlextractedhasarticleurlkeywords": "false",
    "httpheadercontentsecuritypolicy": null,
    "licensee": null,
    "documentreference": "https://www.nab.com.au/business/calculators",
    "httpheaderxxssprotection": null,
    "dcdescription": null,
    "dateerror": null,
    "httpheaderxakamaitransformed": null,
    "collectordepth": "1",
    "googlesiteverification": null,
    "taxonomy": null,
    "fbpageid": "174238599281322",
    "ogurl": "https://www.nab.com.au/business/calculators",
    "ogtype": "website",
    "httpheaderxframeoptions": null,
    "collectorreferencedurls": null,
    "collectorreferrerlinktext": null,
    "httpheaderdate": "Mon, 17 Mar 2025 00:02:26 GMT",
    "uripath": null,
    "searchsuggestions": [],
    "ogtitle": "Business calculators",
    "content": "   Skip to login   Skip to main content   Skip to chat     Business     Calculators   Business calculators   Business tools, calculators and templates to help you calculate loan repayments, manage cash flow and run your business.    Tools and calculators to manage and improve your business   Equipment finance repayment calculator   Find out how much your repayments might be for financing equipment, business cars, utes, vans, machinery and more.    Equipment finance repayment calculator   Business loan repayment calculator   Compare the different loan terms, fees and interest options and work out the best repayment plan for your business.    Business loan repayment calculator   Business tools   Use our easy tools, calculators, forecasts and checklists to help you assess and improve your business.    Business tools   Help me choose the right business loan   Not sure where to start with business finance? Use our easy business loan selector tool.    Help me choose the right business loan   Business plan template   Creating your own business plan doesn\u2019t have to be difficult \u2013 you just need to set aside some time to work through the various elements. Try out our business plan template today.    Business plan template   Help me choose the right business banking solution   Looking for the best online banking platform for your business? Use our easy online platform selector tool.    Help me choose the right business banking solution   Business tips   Starting out   Starting a small business? These tips, tools and customer case studies will help you take the first important steps to success.    Growing your business   Whether you\u2019re hiring staff or securing financing, our tips can help you grow your business.    Managing   Tips and tools to help you keep your business running profitably, from writing a business plan to managing cash flow and tax.    Business products that might interest you   Loans and finance   Starting a business or looking to expand? Our range of business loans, overdrafts, equipment and trade finance options can help you achieve your goals.    Business credit cards   Earn rewards points and manage business expenses with our range of business credit cards.    Business bank accounts   Get your business banking set up with business accounts that suit your different needs.    Get in touch   Contact us   Explore our business banking contact information and get support with a wide range of products, services and topics.    View all business banking contacts   Visit a NAB branch   Our business bankers are located all around Australia.    Find a NAB business banking centre   Call back request   Let\u2019s talk about business banking.    Business banking call back request   Important information    This section contains Important Information relevant to the page you are viewing, but you can't see it because you have JavaScript disabled on your browser.\u00a0Please enable JavaScript and come back so you can see the complete page.\u00a0It's important that you read the Important Information in this section before acting on any information on this page.    Apologies but the Important Information section you are trying to view is not displaying properly at the moment. Please refresh the page or try again later.   ",
    "httpheaderxcheckcacheable": null,
    "sitename": null,
    "htmlextractedtrainingdatacategory": null,
    "htmlextractedhasbenefitsandfeatures": null,
    "phone": null,
    "htmlextractedh1": [
        "Business calculators"
    ],
    "email": null,
    "access": "v3",
    "breadcrumb": null,
    "htmlextractedhasgetstarted": "false",
    "uriparams": null,
    "htmlextractedhasarticletags": null,
    "principlename": null,
    "facebook": null,
    "origintrial": null,
    "contenttypehint": null,
    "age": null,
    "documentcontenttype": "text/html",
    "contentencoding": "UTF-8",
    "viewport": "width=device-width, initial-scale=1",
    "htmlextractedfieldtemplate": "/conf/nab/settings/wcm/templates/content-category",
    "contentpurpose": null,
    "httpheadercontentencoding": null,
    "urihost": null,
    "advisernames": null,
    "collectorsitemaplastmod": null,
    "fax": null,
    "httpheadercachecontrol": "max-age=1142",
    "httpheadercontentlength": null,
    "uripathparseerror": null,
    "created": "2025-03-17T11:02:26Z",
    "description": "NAB has a range of business calculators and tools, along with a national network of business bankers to help you.",
    "findlocationid": null,
    "robots": "index,follow",
    "htmlextractedurlkeywords": "https www nab com au business calculators",
    "httpheaderxcontenttypeoptions": null,
    "id": "aHR0cHM6Ly93d3cubmFiLmNvbS5hdS9idXNpbmVzcy9jYWxjdWxhdG9ycw",
    "crawltime": "2025-03-17T11:02:28Z",
    "collectorcontenttype": "text/html",
    "searchrefiners": "Tools and Calculators",
    "website": null,
    "fallbacksnippet": null,
    "twittertitle": "Business calculators",
    "htmlextractedhastoolsurlkeywords": "true",
    "collectorcontentencoding": "UTF-8",
    "collection": [
        "nabcq5current"
    ],
    "datepublished": null,
    "path": "DOMAINSTART/business/calculators",
    "htmlextractedoutboundlinkcount": "353",
    "twittercard": "summary",
    "principleimage": null,
    "xuacompatible": null,
    "documentcontentencoding": "UTF-8",
    "lastmodified": "2025-03-17T11:02:28Z",
    "datasource": "www.nab.com.au",
    "htmlextractedhasenquire": "false",
    "latitude": null,
    "xparsedby": "org.apache.tika.parser.DefaultParser",
    "fbadmins": null,
    "encoding": null,
    "state": null,
    "uriprotocol": null,
    "datepub": null,
    "httpheaderxakamaipragmaclientip": null,
    "twittersite": "@nab",
    "extension": "html",
    "httpheadersetcookie": null,
    "collectoriscrawlnew": "true",
    "filename": "None",
    "htmlextractedsection": "business",
    "editor": null,
    "httpheaderetag": null,
    "linkedin": null,
    "searchrefinersall": [
        "Tools and Calculators"
    ],
    "htmlextractedishowto": null,
    "htmlextractedurlsegmentcount": "2",
    "collectorreferrerreference": null,
    "httpheaderstricttransportsecurity": null,
    "topicarea": null,
    "suburb": null,
    "address": null,
    "htmlextractedhasproductdiv": "false",
    "htmlextractedhasbenefitandfeaturestext": "false",
    "httpheaderconnection": "keep-alive",
    "modified": "2025-03-17T11:02:28Z",
    "htmlextractedhasgetincontact": "false",
    "keywords": [],
    "systemtitle": null,
    "category": "Tools and Calculators",
    "pdfdocinfosubject": null,
    "htmlextractedh3": [
        "Tools and calculators",
        "You may be interested in",
        "Offer $0 application fee (save $250)",
        "View our research and insights hub",
        "$0 international transfer fee",
        "New Get a 6-month free trial with NAB Bookkeeper",
        "You might be interested in",
        "Unsecured business finance",
        "Related tools and calculators",
        "Offer 200,000 bonus Qantas Points",
        "Related tools and help",
        "Related tools and help",
        "NAB Connect training",
        "$0 international transfer fees",
        "More about sustainability",
        "Need more help?",
        "Troubleshooting guides",
        "Need more help?",
        "Equipment finance repayment calculator",
        "Business loan repayment calculator",
        "Business tools",
        "Help me choose the right business loan",
        "Business plan template",
        "Help me choose the right business banking solution",
        "Starting out",
        "Growing your business",
        "Managing",
        "Loans and finance",
        "Business credit cards",
        "Business bank accounts",
        "Contact us",
        "Visit a NAB branch",
        "Call back request"
    ],
    "principletitle": null,
    "location": null,
    "httpheaderacceptranges": null,
    "httpheadertransferencoding": null,
    "subcollection": [],
    "summary": null,
    "httpheadervary": "Accept-Encoding",
    "dctitle": "Business calculators and financial tools | Business support - NAB",
    "twitter": null,
    "tags": null,
    "docsize": null,
    "url": "https://www.nab.com.au/business/calculators",
    "htmlextractedhasapplynow": "false",
    "contenttype": "text/html",
    "crawledat": "1742169748432",
    "title": "Business calculators",
    "httpheaderexpires": null,
    "httpheaderxserial": null,
    "httpheaderxakamaisslclientsid": null,
    "twitteraccountid": "7302852",
    "ogdescription": "Use NAB\u2019s range of business calculators, tools and templates to help you start a business, manage cash flow and calculate business loan repayments.",
    "htmlextractedhasgettingstarted": "false",
    "date": "Mon, 17 Mar 2025 00:02:26 GMT",
    "htmlextractedinputcount": "2",
    "collectorreferrerlinktag": null,
    "postcode": null,
    "contentfamily": "html",
    "document": null,
    "author": null,
    "contentlocation": "https://www.nab.com.au/business/calculators",
    "metachecksum": null,
    "longitude": null,
    "htmlextractedh2": [
        "Latest offers",
        "Update your browser.",
        "NAB Mobile Banking app",
        "Apply for NAB Now Pay Later in under 90 seconds",
        "Have we contacted you about confirming your details?",
        "Women in Business",
        "The Morning Call Podcast",
        "The Morning Call Podcast",
        "Helping you stay safe from scams",
        "Have we contacted you about confirming your details?",
        "Have we contacted you about confirming your details?",
        "Tools and calculators to manage and improve your business",
        "Business tips",
        "Business products that might interest you",
        "Get in touch",
        "Important information",
        "Quick links",
        "Quick links",
        "Policies and terms",
        "Policies and terms",
        "Connect with us",
        "Connect with us"
    ],
    "documentcontentfamily": "html",
    "httpheadercontenttype": "text/html",
    "httpheaderlastmodified": null,
    "twitterdescription": "Use NAB\u2019s range of business calculators, tools and templates to help you start a business, manage cash flow and calculate business loan repayments."
}