{
    "htmlextractedmetarefiners": null,
    "postaladdress": null,
    "formatdetection": null,
    "locationgeo": null,
    "htmlextractedisinmegamenu": "false",
    "htmlextractedhasarticleurlkeywords": "false",
    "httpheadercontentsecuritypolicy": null,
    "licensee": null,
    "documentreference": "https://www.nab.com.au/about-us/board-of-directors/andrew-irvine",
    "httpheaderxxssprotection": null,
    "dcdescription": null,
    "dateerror": null,
    "httpheaderxakamaitransformed": null,
    "collectordepth": "0",
    "googlesiteverification": null,
    "taxonomy": null,
    "fbpageid": "174238599281322",
    "ogurl": "https://www.nab.com.au/about-us/board-of-directors/andrew-irvine",
    "ogtype": "website",
    "httpheaderxframeoptions": null,
    "collectorreferencedurls": "https://www.nab.com.au/personal/online-banking/fast-payments",
    "collectorreferrerlinktext": null,
    "httpheaderdate": "Mon, 17 Mar 2025 01:09:40 GMT",
    "uripath": null,
    "searchsuggestions": [],
    "ogtitle": "Andrew Irvine",
    "content": "   Skip to login   Skip to main content   Skip to chat     About us     Board of Directors     Andrew Irvine   Andrew Irvine   Managing Director and Group Chief Executive Officer   BSc Business Management (Hons), MBA    Term of office    Managing Director and Group Chief Executive Officer\u00a0since April 2024.    Independent    No\u00a0    Industry experience    Andrew has more than 25 years of experience in the financial services industry. Andrew joined NAB in 2020 as Group Executive, Business and Private Banking following a 12 year career with Bank of Montreal where he held a number of executive roles, including as Head of Canadian Business Banking where he had end-to-end accountability for the division. Prior to Bank of Montreal, Andrew was with strategy consulting firm, McKinsey & Company, between 2002 and 2008 in Canada, including as Associate Partner with specific focus on clients in the financial services industry. Before working in consulting, Andrew worked in investment banking at Credit Agricole in London.    Andrew has a deep understanding of customers developed over a career in banking and significant leadership experience in using data, insights and technology to meet customer needs.    Other business and market experience    Andrew has extensive experience in leading organisations through significant change, growth and to a market leading position.    Other relevant interests    Andrew's other interests include Australian Banking Association (Chair) and the Financial Markets Foundation for Children (Director).    Board of Directors     Philip Chronican    Andrew Irvine    Kathryn Fagg    Christine Fellowes    Warwick Hunt    Carolyn Kay    Alison Kitchen    Simon McKeon    Ann Sherry   Important information    This section contains Important Information relevant to the page you are viewing, but you can't see it because you have JavaScript disabled on your browser.\u00a0Please enable JavaScript and come back so you can see the complete page.\u00a0It's important that you read the Important Information in this section before acting on any information on this page.    Apologies but the Important Information section you are trying to view is not displaying properly at the moment. Please refresh the page or try again later.   ",
    "httpheaderxcheckcacheable": null,
    "sitename": null,
    "htmlextractedtrainingdatacategory": null,
    "htmlextractedhasbenefitsandfeatures": null,
    "phone": null,
    "htmlextractedh1": [
        "Andrew Irvine"
    ],
    "email": null,
    "access": "v3",
    "breadcrumb": null,
    "htmlextractedhasgetstarted": "false",
    "uriparams": null,
    "htmlextractedhasarticletags": null,
    "principlename": null,
    "facebook": null,
    "origintrial": null,
    "contenttypehint": null,
    "age": null,
    "documentcontenttype": "text/html",
    "contentencoding": "UTF-8",
    "viewport": "width=device-width, initial-scale=1",
    "htmlextractedfieldtemplate": "/conf/nab/settings/wcm/templates/article-and-service-detail",
    "contentpurpose": null,
    "httpheadercontentencoding": null,
    "urihost": null,
    "advisernames": null,
    "collectorsitemaplastmod": "2024-12-20T19:06:50+11:00",
    "fax": null,
    "httpheadercachecontrol": "max-age=1200",
    "httpheadercontentlength": null,
    "uripathparseerror": null,
    "created": "2025-03-17T12:09:40Z",
    "description": "Philip Chronican has over 35 years of experience in banking and finance.",
    "findlocationid": null,
    "robots": "index,follow",
    "htmlextractedurlkeywords": "https www nab com au about us board of directors andrew irvine",
    "httpheaderxcontenttypeoptions": null,
    "id": "aHR0cHM6Ly93d3cubmFiLmNvbS5hdS9hYm91dC11cy9ib2FyZC1vZi1kaXJlY3RvcnMvYW5kcmV3LWlydmluZQ",
    "crawltime": "2025-03-17T12:09:42Z",
    "collectorcontenttype": "text/html",
    "searchrefiners": "Articles",
    "website": null,
    "fallbacksnippet": null,
    "twittertitle": "Andrew Irvine",
    "htmlextractedhastoolsurlkeywords": "false",
    "collectorcontentencoding": "UTF-8",
    "collection": [
        "nabcq5current"
    ],
    "datepublished": null,
    "path": "DOMAINSTART/about-us/board-of-directors/andrew-irvine",
    "htmlextractedoutboundlinkcount": "348",
    "twittercard": "summary",
    "principleimage": null,
    "xuacompatible": null,
    "documentcontentencoding": "ISO-8859-1",
    "lastmodified": "2025-03-17T12:09:42Z",
    "datasource": "www.nab.com.au",
    "htmlextractedhasenquire": "false",
    "latitude": null,
    "xparsedby": "org.apache.tika.parser.DefaultParser",
    "fbadmins": null,
    "encoding": null,
    "state": null,
    "uriprotocol": null,
    "datepub": null,
    "httpheaderxakamaipragmaclientip": null,
    "twittersite": "@nab",
    "extension": "html",
    "httpheadersetcookie": null,
    "collectoriscrawlnew": "true",
    "filename": "None",
    "htmlextractedsection": "about-us",
    "editor": null,
    "httpheaderetag": null,
    "linkedin": null,
    "searchrefinersall": [
        "Articles"
    ],
    "htmlextractedishowto": null,
    "htmlextractedurlsegmentcount": "3",
    "collectorreferrerreference": null,
    "httpheaderstricttransportsecurity": null,
    "topicarea": null,
    "suburb": null,
    "address": null,
    "htmlextractedhasproductdiv": "false",
    "htmlextractedhasbenefitandfeaturestext": "false",
    "httpheaderconnection": "keep-alive",
    "modified": "2025-03-17T12:09:42Z",
    "htmlextractedhasgetincontact": "false",
    "keywords": [],
    "systemtitle": null,
    "category": "Articles",
    "pdfdocinfosubject": null,
    "htmlextractedh3": [
        "Tools and calculators",
        "You may be interested in",
        "Offer $0 application fee (save $250)",
        "View our research and insights hub",
        "$0 international transfer fee",
        "New Get a 6-month free trial with NAB Bookkeeper",
        "You might be interested in",
        "Unsecured business finance",
        "Related tools and calculators",
        "Offer 200,000 bonus Qantas Points",
        "Related tools and help",
        "Related tools and help",
        "NAB Connect training",
        "$0 international transfer fees",
        "More about sustainability",
        "Need more help?",
        "Troubleshooting guides",
        "Need more help?",
        "Term of office",
        "Independent",
        "Industry experience",
        "Other business and market experience",
        "Other relevant interests"
    ],
    "principletitle": null,
    "location": null,
    "httpheaderacceptranges": null,
    "httpheadertransferencoding": null,
    "subcollection": [],
    "summary": null,
    "httpheadervary": "Accept-Encoding",
    "dctitle": "Andrew Irvine | Board of Directors - NAB",
    "twitter": null,
    "tags": null,
    "docsize": null,
    "url": "https://www.nab.com.au/about-us/board-of-directors/andrew-irvine",
    "htmlextractedhasapplynow": "false",
    "contenttype": "text/html",
    "crawledat": "1742173782455",
    "title": "Andrew Irvine",
    "httpheaderexpires": null,
    "httpheaderxserial": null,
    "httpheaderxakamaisslclientsid": null,
    "twitteraccountid": "7302852",
    "ogdescription": "Andrew Irvine is Managing Director and Group Chief Executive Officer with more than 25 years' financial services experience.",
    "htmlextractedhasgettingstarted": "false",
    "date": "Mon, 17 Mar 2025 01:09:40 GMT",
    "htmlextractedinputcount": "2",
    "collectorreferrerlinktag": null,
    "postcode": null,
    "contentfamily": "html",
    "document": null,
    "author": null,
    "contentlocation": "https://www.nab.com.au/about-us/board-of-directors/andrew-irvine",
    "metachecksum": null,
    "longitude": null,
    "htmlextractedh2": [
        "Latest offers",
        "Update your browser.",
        "NAB Mobile Banking app",
        "Apply for NAB Now Pay Later in under 90 seconds",
        "Have we contacted you about confirming your details?",
        "Women in Business",
        "The Morning Call Podcast",
        "The Morning Call Podcast",
        "Helping you stay safe from scams",
        "Have we contacted you about confirming your details?",
        "Have we contacted you about confirming your details?",
        "Managing Director and Group Chief Executive Officer",
        "Board of Directors",
        "Important information",
        "Quick links",
        "Quick links",
        "Policies and terms",
        "Policies and terms",
        "Connect with us",
        "Connect with us"
    ],
    "documentcontentfamily": "html",
    "httpheadercontenttype": "text/html",
    "httpheaderlastmodified": null,
    "twitterdescription": "Andrew Irvine is Managing Director and Group Chief Executive Officer with more than 25 years' financial services experience."
}